{
  "name": "React Native",
  "description": "A framework for building native apps with React.",
  "Notes": "Depend on GNUstl and WebKit",
  "author": "Facebook",
  "homepage": "https://github.com/facebook/react-native",
  "license": {
    "spdx": "MIT",
    "type": "permissive",
    "url": "https://github.com/facebook/react-native/blob/master/LICENSE"
  },
  "language": "native",
  "keywords": [
    "react",
    "reactnative",
    "facebook",
    "webkit",
    "webcore"
  ],
  "symbols": [
    "LogcatSink",
    "OpaqueJSClass",
    "OpaqueJSString",
    "TaggedLogcatSink",
    "facebook::react:"
  ]
}
