{
  "name": "Xiph Vorbis",
  "description": "Vorbis is a general purpose audio and music encoding format contemporary to MPEG-4's AAC and TwinVQ, the next generation beyond MPEG audio layer 3.",
  "Notes": "",
  "author": "Xiph.Org Foundation",
  "homepage": "https://github.com/xiph/vorbis",
  "license": {
    "spdx": "BSD-3-Clause",
    "type": "permissive",
    "url": "https://github.com/xiph/vorbis/blob/master/COPYING"
  },
  "language": "native",
  "keywords": [
    "Xiph",
    "Vorbis",
    "ffmpeg"
  ],
  "symbols": [
    "OggOpusEncoder",
    "liboggencoder"
  ]
}
