{
    "publisher": "Daniel Lew",
    "updated": "2022-06-12",
    "package": "Joda-Time library",
    "license": "Apache-2.0",
    "symbols": [
        "OldDefaultJoda",
        "JodaSampleActivity",
        "jodaDateUtils",
        "jodaJodaTimeAndroid",
        "joda_keep",
        "jodaResUtils",
        "JodaSampleActivity",
        "JodaTimeAndroid",
        "jodasample",
        "jodaTzDataPlugin",
        "jodaTzDataPluginExtension",
        "jodaTimeZoneChangedReceiver",
        "jodaResourceZoneInfoProvider",
        "qjoda",
        "mDefaultJodaTz",
        "jodaCompileTzDataTask",
        "activity_joda_sample",
        "JodaTimeInitializer",
        "jodatest",
        "jodaJodaTimeInitializer",
        "joda"
    ]
}
